[
  {
    "word": "plot",
    "phonetic": "/plˈɑt/",
    "meaning": "cốt truyện",
    "example": "The plot was unpredictable and engaging."
  },
  {
    "word": "character development",
    "phonetic": "/kˈerɪktɝ dɪvˈelʌpmʌnt/",
    "meaning": "phát triển nhân vật",
    "example": "Character development makes stories more believable."
  },
  {
    "word": "genre",
    "phonetic": "/ʒˈɑnrʌ/",
    "meaning": "thể loại",
    "example": "This genre is popular among young adults."
  },
  {
    "word": "director",
    "phonetic": "/dɝˈektɝ/",
    "meaning": "đạo diễn",
    "example": "The director is known for realistic storytelling."
  },
  {
    "word": "screenplay",
    "phonetic": "/skrˈinplˌeɪ/",
    "meaning": "kịch bản",
    "example": "A strong screenplay keeps the film coherent."
  },
  {
    "word": "cinematography",
    "phonetic": "/sˌɪnɪmʌtˈɑɡrʌfi/",
    "meaning": "quay phim",
    "example": "Cinematography creates mood and atmosphere."
  },
  {
    "word": "soundtrack",
    "phonetic": "/sˈaʊndtrˌæk/",
    "meaning": "nhạc phim",
    "example": "The soundtrack enhances emotional scenes."
  },
  {
    "word": "special effects",
    "phonetic": "/spˈeʃʌl ɪfˈekts/",
    "meaning": "kỹ xảo",
    "example": "Special effects improve immersion if used well."
  },
  {
    "word": "adaptation",
    "phonetic": "/ˌædʌptˈeɪʃʌn/",
    "meaning": "chuyển thể",
    "example": "The adaptation stayed faithful to the novel."
  },
  {
    "word": "novel",
    "phonetic": "/nˈɑvʌl/",
    "meaning": "tiểu thuyết",
    "example": "The novel explores identity and freedom."
  },
  {
    "word": "fiction",
    "phonetic": "/fˈɪkʃʌn/",
    "meaning": "hư cấu",
    "example": "Fiction helps readers imagine different worlds."
  },
  {
    "word": "non-fiction",
    "phonetic": "/nˈɑn fˈɪkʃʌn/",
    "meaning": "phi hư cấu",
    "example": "Non-fiction provides factual information."
  },
  {
    "word": "bestseller",
    "phonetic": "/bˈestsˈelɝ/",
    "meaning": "sách bán chạy",
    "example": "The bestseller was translated into many languages."
  },
  {
    "word": "author",
    "phonetic": "/ˈɔθɝ/",
    "meaning": "tác giả",
    "example": "The author writes in a clear style."
  },
  {
    "word": "narrative",
    "phonetic": "/nˈærʌtɪv/",
    "meaning": "tường thuật",
    "example": "The narrative shifts between past and present."
  },
  {
    "word": "theme",
    "phonetic": "/θˈim/",
    "meaning": "chủ đề",
    "example": "A key theme is tradition versus modernity."
  },
  {
    "word": "symbolism",
    "phonetic": "/sˈɪmbʌlˌɪzʌm/",
    "meaning": "biểu tượng",
    "example": "Symbolism adds deeper meaning to stories."
  },
  {
    "word": "documentary",
    "phonetic": "/dˌɑkjʌmˈentɝi/",
    "meaning": "phim tài liệu",
    "example": "Documentaries raise awareness about social issues."
  },
  {
    "word": "biography",
    "phonetic": "/baɪˈɑɡrʌfi/",
    "meaning": "tiểu sử",
    "example": "A biography reveals challenges behind success."
  },
  {
    "word": "literary classic",
    "phonetic": "/lˈɪtɝˌeri klˈæsɪk/",
    "meaning": "tác phẩm kinh điển",
    "example": "Literary classics remain relevant across generations."
  }
]